sevdesk/__init__.py
sevdesk/client.py
sevdesk/base/basecontroller.py
sevdesk/controllers/accountingcontact_controller.py
sevdesk/controllers/basics_controller.py
sevdesk/controllers/checkaccount_controller.py
sevdesk/controllers/checkaccounttransaction_controller.py
sevdesk/controllers/communicationway_controller.py
sevdesk/controllers/contact_controller.py
sevdesk/controllers/contactaddress_controller.py
sevdesk/controllers/contactfield_controller.py
sevdesk/controllers/creditnote_controller.py
sevdesk/controllers/creditnotepos_controller.py
sevdesk/controllers/export_controller.py
sevdesk/controllers/invoice_controller.py
sevdesk/controllers/invoicepos_controller.py
sevdesk/controllers/layout_controller.py
sevdesk/controllers/order_controller.py
sevdesk/controllers/orderpos_controller.py
sevdesk/controllers/part_controller.py
sevdesk/controllers/report_controller.py
sevdesk/controllers/tag_controller.py
sevdesk/controllers/voucher_controller.py
sevdesk/controllers/voucherpos_controller.py
sevdesk/converters/accountdatev.py
sevdesk/converters/accountingtype.py
sevdesk/converters/addresscountry.py
sevdesk/converters/category.py
sevdesk/converters/checkaccount.py
sevdesk/converters/contact.py
sevdesk/converters/contactcustomfieldsetting.py
sevdesk/converters/contactperson.py
sevdesk/converters/costcentre.py
sevdesk/converters/country.py
sevdesk/converters/createuser.py
sevdesk/converters/creditnote.py
sevdesk/converters/discountdelete.py
sevdesk/converters/document.py
sevdesk/converters/error.py
sevdesk/converters/estimatedaccountingtype.py
sevdesk/converters/invoice.py
sevdesk/converters/key.py
sevdesk/converters/metadaten.py
sevdesk/converters/object.py
sevdesk/converters/object_.py
sevdesk/converters/order.py
sevdesk/converters/origin.py
sevdesk/converters/parent.py
sevdesk/converters/part.py
sevdesk/converters/paymentmethod.py
sevdesk/converters/sevclient.py
sevdesk/converters/sourcetransaction.py
sevdesk/converters/supplier.py
sevdesk/converters/tag.py
sevdesk-0.2.2.dist-info/licenses/LICENSE
sevdesk-0.2.2.dist-info/METADATA
sevdesk-0.2.2.dist-info/WHEEL
sevdesk-0.2.2.dist-info/top_level.txt
sevdesk-0.2.2.dist-info/RECORD
