Metadata-Version: 2.4
Name: sevdesk
Version: 0.2.2
Summary: A Python client for the sevDesk API, automatically generated from the OpenAPI specification
Author: Claude
Author-email: Maximilian Clemens <maximilian.clemens@gamma.red>
License: MIT
Project-URL: Homepage, https://github.com/MaximilianClemens/python-sevdesk
Project-URL: Repository, https://github.com/MaximilianClemens/python-sevdesk
Project-URL: Issues, https://github.com/MaximilianClemens/python-sevdesk/issues
Keywords: sevdesk,api,client,accounting
Classifier: Development Status :: 3 - Alpha
Classifier: Intended Audience :: Developers
Classifier: License :: OSI Approved :: MIT License
Classifier: Programming Language :: Python :: 3
Classifier: Programming Language :: Python :: 3.8
Classifier: Programming Language :: Python :: 3.9
Classifier: Programming Language :: Python :: 3.10
Classifier: Programming Language :: Python :: 3.11
Classifier: Programming Language :: Python :: 3.12
Requires-Python: >=3.8
License-File: LICENSE
Requires-Dist: pydantic
Requires-Dist: requests
Requires-Dist: PyYAML
Requires-Dist: jinja2
Dynamic: license-file
